aa/__init__.py
aa/_version_git.py
aa/ca.py
aa/data.py
aa/epics_event_pb2.py
aa/fetcher.py
aa/js.py
aa/pb.py
aa/rest.py
aa/storage.py
aa/utils.py
aa/__pycache__/_version_git.cpython-37.pyc
aapy-0.12.dist-info/LICENSE
aapy-0.12.dist-info/METADATA
aapy-0.12.dist-info/NOTICE
aapy-0.12.dist-info/WHEEL
aapy-0.12.dist-info/top_level.txt
aapy-0.12.dist-info/RECORD
