Metadata-Version: 2.1
Name: aapy
Version: 0.12
Summary: Python client for the EPICS Archiver Appliance
Home-page: https://github.com/dls-controls/aapy
Author: Will Rogers
Author-email: will.rogers@diamond.ac.uk
License: Apache License 2.0
Platform: UNKNOWN
Classifier: License :: OSI Approved :: Apache Software License
Classifier: Programming Language :: Python :: 3.7
Classifier: Programming Language :: Python :: 3.8
Classifier: Programming Language :: Python :: 3.9
License-File: LICENSE
License-File: NOTICE
Requires-Dist: numpy
Requires-Dist: protobuf
Requires-Dist: pytz
Requires-Dist: requests
Requires-Dist: tzlocal
